slick/__init__.py
slick/models.py
slick/settings.py
slick/static/.DS_Store
slick/static/bootstrap/.DS_Store
slick/static/bootstrap/js/.DS_Store
slick/static/bootstrap/js/dist/alert.js
slick/static/bootstrap/js/dist/alert.js.map
slick/static/bootstrap/js/dist/button.js
slick/static/bootstrap/js/dist/button.js.map
slick/static/bootstrap/js/dist/carousel.js
slick/static/bootstrap/js/dist/carousel.js.map
slick/static/bootstrap/js/dist/collapse.js
slick/static/bootstrap/js/dist/collapse.js.map
slick/static/bootstrap/js/dist/dropdown.js
slick/static/bootstrap/js/dist/dropdown.js.map
slick/static/bootstrap/js/dist/index.js
slick/static/bootstrap/js/dist/index.js.map
slick/static/bootstrap/js/dist/modal.js
slick/static/bootstrap/js/dist/modal.js.map
slick/static/bootstrap/js/dist/popover.js
slick/static/bootstrap/js/dist/popover.js.map
slick/static/bootstrap/js/dist/scrollspy.js
slick/static/bootstrap/js/dist/scrollspy.js.map
slick/static/bootstrap/js/dist/tab.js
slick/static/bootstrap/js/dist/tab.js.map
slick/static/bootstrap/js/dist/tooltip.js
slick/static/bootstrap/js/dist/tooltip.js.map
slick/static/bootstrap/js/dist/util.js
slick/static/bootstrap/js/dist/util.js.map
slick/static/bootstrap/js/src/alert.js
slick/static/bootstrap/js/src/button.js
slick/static/bootstrap/js/src/carousel.js
slick/static/bootstrap/js/src/collapse.js
slick/static/bootstrap/js/src/dropdown.js
slick/static/bootstrap/js/src/index.js
slick/static/bootstrap/js/src/modal.js
slick/static/bootstrap/js/src/popover.js
slick/static/bootstrap/js/src/scrollspy.js
slick/static/bootstrap/js/src/tab.js
slick/static/bootstrap/js/src/tooltip.js
slick/static/bootstrap/js/src/util.js
slick/static/bootstrap/js/tests/README.md
slick/static/bootstrap/js/tests/index.html
slick/static/bootstrap/js/tests/karma.conf.js
slick/static/bootstrap/js/tests/unit/.eslintrc.json
slick/static/bootstrap/js/tests/unit/alert.js
slick/static/bootstrap/js/tests/unit/button.js
slick/static/bootstrap/js/tests/unit/carousel.js
django_slick-0.3.0.dist-info/LICENSE
django_slick-0.3.0.dist-info/METADATA
django_slick-0.3.0.dist-info/WHEEL
django_slick-0.3.0.dist-info/top_level.txt
django_slick-0.3.0.dist-info/RECORD
